[
  {
    "구분": "교양필수",
    "학수번호": "GELI005",
    "교과목명": "학문세계의탐구 I",
    "학년": 1.0,
    "학기": null,
    "필수선수": null,
    "권장선수": null,
    "실험실습": null,
    "세부전공": null,
    "학점": 3,
    "시간": 3,
    "전공역량": null,
    "대학": "이과대학",
    "학과": "수학과",
    "개설학과": null,
    "내용": null,
    "메모": null,
    "개설횟수": 1
  },
  {
    "구분": "교양필수",
    "학수번호": "GEWR002",
    "교과목명": "글쓰기",
    "학년": 1.0,
    "학기": 1.0,
    "필수선수": null,
    "권장선수": null,
    "실험실습": null,
    "세부전공": null,
    "학점": 3,
    "시간": 3,
    "전공역량": null,
    "대학": "이과대학",
    "학과": "수학과",
    "개설학과": null,
    "내용": null,
    "메모": null,
    "개설횟수": 1
  },
  {
    "구분": "교양필수",
    "학수번호": "IFLS800",
    "교과목명": "Academic English I",
    "학년": 1.0,
    "학기": null,
    "필수선수": null,
    "권장선수": null,
    "실험실습": null,
    "세부전공": null,
    "학점": 2,
    "시간": 2,
    "전공역량": null,
    "대학": "이과대학",
    "학과": "수학과",
    "개설학과": null,
    "내용": null,
    "메모": null,
    "개설횟수": 1
  },
  {
    "구분": "교양필수",
    "학수번호": "GEKS007",
    "교과목명": "[진로창업]1학년세미나 I",
    "학년": 1.0,
    "학기": 1.0,
    "필수선수": null,
    "권장선수": null,
    "실험실습": null,
    "세부전공": null,
    "학점": 1,
    "시간": 1,
    "전공역량": null,
    "대학": "이과대학",
    "학과": "수학과",
    "개설학과": null,
    "내용": null,
    "메모": null,
    "개설횟수": 1
  },
  {
    "구분": "교양필수",
    "학수번호": "GEKS008",
    "교과목명": "[진로창업]1학년세미나 I",
    "학년": 1.0,
    "학기": 2.0,
    "필수선수": null,
    "권장선수": null,
    "실험실습": null,
    "세부전공": null,
    "학점": 1,
    "시간": 1,
    "전공역량": null,
    "대학": "이과대학",
    "학과": "수학과",
    "개설학과": null,
    "내용": null,
    "메모": null,
    "개설횟수": 1
  },
  {
    "구분": "교양필수",
    "학수번호": "GECT002",
    "교과목명": "[진로창업]SW프로그래밍의기초",
    "학년": 1.0,
    "학기": 1.0,
    "필수선수": null,
    "권장선수": null,
    "실험실습": null,
    "세부전공": null,
    "학점": 3,
    "시간": 3,
    "전공역량": null,
    "대학": "이과대학",
    "학과": "수학과",
    "개설학과": null,
    "내용": null,
    "메모": null,
    "개설횟수": 1
  },
  {
    "구분": "교양필수",
    "학수번호": "GECT003",
    "교과목명": "[진로창업]데이터과학과인공지능",
    "학년": 1.0,
    "학기": 2.0,
    "필수선수": null,
    "권장선수": null,
    "실험실습": null,
    "세부전공": null,
    "학점": 3,
    "시간": 3,
    "전공역량": null,
    "대학": "이과대학",
    "학과": "수학과",
    "개설학과": null,
    "내용": null,
    "메모": null,
    "개설횟수": 0
  },
  {
    "구분": "교양필수",
    "학수번호": "GEBT001",
    "교과목명": "[진로창업]생명과학의세계",
    "학년": 1.0,
    "학기": null,
    "필수선수": null,
    "권장선수": null,
    "실험실습": null,
    "세부전공": null,
    "학점": 3,
    "시간": 3,
    "전공역량": null,
    "대학": "이과대학",
    "학과": "수학과",
    "개설학과": null,
    "내용": null,
    "메모": null,
    "개설횟수": 1
  },
  {
    "구분": "교양선택",
    "학수번호": "MATH161",
    "교과목명": "미적분학및연습I",
    "학년": 1.0,
    "학기": 1.0,
    "필수선수": null,
    "권장선수": null,
    "실험실습": null,
    "세부전공": null,
    "학점": 3,
    "시간": 4,
    "전공역량": null,
    "대학": "이과대학",
    "학과": "수학과",
    "개설학과": "수학과",
    "내용": null,
    "메모": null,
    "개설횟수": 5
  },
  {
    "구분": "교양선택",
    "학수번호": "MATH162",
    "교과목명": "미적분학및연습II",
    "학년": 1.0,
    "학기": 2.0,
    "필수선수": null,
    "권장선수": null,
    "실험실습": null,
    "세부전공": null,
    "학점": 3,
    "시간": 4,
    "전공역량": null,
    "대학": "이과대학",
    "학과": "수학과",
    "개설학과": "수학과",
    "내용": null,
    "메모": null,
    "개설횟수": 5
  },
  {
    "구분": "교양선택",
    "학수번호": "PHYS151",
    "교과목명": "일반물리학연습 I",
    "학년": 1.0,
    "학기": null,
    "필수선수": null,
    "권장선수": null,
    "실험실습": null,
    "세부전공": null,
    "학점": 3,
    "시간": 3,
    "전공역량": null,
    "대학": "이과대학",
    "학과": "수학과",
    "개설학과": "물리학과",
    "내용": null,
    "메모": null,
    "개설횟수": 5
  },
  {
    "구분": "교양선택",
    "학수번호": "PHYS152",
    "교과목명": "일반물리학연습 II",
    "학년": 1.0,
    "학기": null,
    "필수선수": null,
    "권장선수": null,
    "실험실습": null,
    "세부전공": null,
    "학점": 3,
    "시간": 3,
    "전공역량": null,
    "대학": "이과대학",
    "학과": "수학과",
    "개설학과": "물리학과",
    "내용": null,
    "메모": null,
    "개설횟수": 5
  },
  {
    "구분": "교양선택",
    "학수번호": "PHYS161",
    "교과목명": "일반물리학실험 I",
    "학년": 1.0,
    "학기": null,
    "필수선수": null,
    "권장선수": null,
    "실험실습": null,
    "세부전공": null,
    "학점": 1,
    "시간": 3,
    "전공역량": null,
    "대학": "이과대학",
    "학과": "수학과",
    "개설학과": "물리학과",
    "내용": null,
    "메모": null,
    "개설횟수": 5
  },
  {
    "구분": "교양선택",
    "학수번호": "PHYS162",
    "교과목명": "일반물리학실험 II",
    "학년": 1.0,
    "학기": null,
    "필수선수": null,
    "권장선수": null,
    "실험실습": null,
    "세부전공": null,
    "학점": 1,
    "시간": 3,
    "전공역량": null,
    "대학": "이과대학",
    "학과": "수학과",
    "개설학과": "물리학과",
    "내용": null,
    "메모": null,
    "개설횟수": 5
  },
  {
    "구분": "교양선택",
    "학수번호": "CHEM151",
    "교과목명": "일반화학및연습 I",
    "학년": 1.0,
    "학기": null,
    "필수선수": null,
    "권장선수": null,
    "실험실습": null,
    "세부전공": null,
    "학점": 3,
    "시간": 3,
    "전공역량": null,
    "대학": "이과대학",
    "학과": "수학과",
    "개설학과": "화학과",
    "내용": null,
    "메모": null,
    "개설횟수": 5
  },
  {
    "구분": "교양선택",
    "학수번호": "CHEM152",
    "교과목명": "일반화학및연습 II",
    "학년": 1.0,
    "학기": null,
    "필수선수": null,
    "권장선수": null,
    "실험실습": null,
    "세부전공": null,
    "학점": 3,
    "시간": 3,
    "전공역량": null,
    "대학": "이과대학",
    "학과": "수학과",
    "개설학과": "화학과",
    "내용": null,
    "메모": null,
    "개설횟수": 5
  },
  {
    "구분": "교양선택",
    "학수번호": "CHEM153",
    "교과목명": "일반화학실험 I",
    "학년": 1.0,
    "학기": null,
    "필수선수": null,
    "권장선수": null,
    "실험실습": null,
    "세부전공": null,
    "학점": 1,
    "시간": 3,
    "전공역량": null,
    "대학": "이과대학",
    "학과": "수학과",
    "개설학과": "화학과",
    "내용": null,
    "메모": null,
    "개설횟수": 5
  },
  {
    "구분": "교양선택",
    "학수번호": "CHEM154",
    "교과목명": "일반화학실험 II",
    "학년": 1.0,
    "학기": null,
    "필수선수": null,
    "권장선수": null,
    "실험실습": null,
    "세부전공": null,
    "학점": 1,
    "시간": 3,
    "전공역량": null,
    "대학": "이과대학",
    "학과": "수학과",
    "개설학과": "화학과",
    "내용": null,
    "메모": null,
    "개설횟수": 5
  },
  {
    "구분": "교양선택",
    "학수번호": "EAES151",
    "교과목명": "지구환경과학및연습 I",
    "학년": 1.0,
    "학기": null,
    "필수선수": null,
    "권장선수": null,
    "실험실습": null,
    "세부전공": null,
    "학점": 3,
    "시간": 3,
    "전공역량": null,
    "대학": "이과대학",
    "학과": "수학과",
    "개설학과": "지구환경과학과",
    "내용": null,
    "메모": null,
    "개설횟수": 5
  },
  {
    "구분": "교양선택",
    "학수번호": "EAES152",
    "교과목명": "지구환경과학및연습 II",
    "학년": 1.0,
    "학기": null,
    "필수선수": null,
    "권장선수": null,
    "실험실습": null,
    "세부전공": null,
    "학점": 3,
    "시간": 3,
    "전공역량": null,
    "대학": "이과대학",
    "학과": "수학과",
    "개설학과": "지구환경과학과",
    "내용": null,
    "메모": null,
    "개설횟수": 5
  },
  {
    "구분": "교양선택",
    "학수번호": "EAES153",
    "교과목명": "지구환경과학실험 I",
    "학년": 1.0,
    "학기": null,
    "필수선수": null,
    "권장선수": null,
    "실험실습": null,
    "세부전공": null,
    "학점": 1,
    "시간": 3,
    "전공역량": null,
    "대학": "이과대학",
    "학과": "수학과",
    "개설학과": "지구환경과학과",
    "내용": null,
    "메모": null,
    "개설횟수": 5
  },
  {
    "구분": "교양선택",
    "학수번호": "EAES154",
    "교과목명": "지구환경과학실험 II",
    "학년": 1.0,
    "학기": null,
    "필수선수": null,
    "권장선수": null,
    "실험실습": null,
    "세부전공": null,
    "학점": 1,
    "시간": 3,
    "전공역량": null,
    "대학": "이과대학",
    "학과": "수학과",
    "개설학과": "지구환경과학과",
    "내용": null,
    "메모": null,
    "개설횟수": 5
  },
  {
    "구분": "교양선택",
    "학수번호": "LIBS151",
    "교과목명": "일반생물학및연습 I",
    "학년": 1.0,
    "학기": null,
    "필수선수": null,
    "권장선수": null,
    "실험실습": null,
    "세부전공": null,
    "학점": 3,
    "시간": 3,
    "전공역량": null,
    "대학": "이과대학",
    "학과": "수학과",
    "개설학과": "생명과학부",
    "내용": null,
    "메모": null,
    "개설횟수": 5
  },
  {
    "구분": "교양선택",
    "학수번호": "LIBS152",
    "교과목명": "일반생물학및연습 II",
    "학년": 1.0,
    "학기": null,
    "필수선수": null,
    "권장선수": null,
    "실험실습": null,
    "세부전공": null,
    "학점": 3,
    "시간": 3,
    "전공역량": null,
    "대학": "이과대학",
    "학과": "수학과",
    "개설학과": "생명과학부",
    "내용": null,
    "메모": null,
    "개설횟수": 5
  },
  {
    "구분": "교양선택",
    "학수번호": "LIBS153",
    "교과목명": "일반생물학실험 I",
    "학년": 1.0,
    "학기": null,
    "필수선수": null,
    "권장선수": null,
    "실험실습": null,
    "세부전공": null,
    "학점": 1,
    "시간": 3,
    "전공역량": null,
    "대학": "이과대학",
    "학과": "수학과",
    "개설학과": "생명과학부",
    "내용": null,
    "메모": null,
    "개설횟수": 5
  },
  {
    "구분": "교양선택",
    "학수번호": "LIBS154",
    "교과목명": "일반생물학실험 II",
    "학년": 1.0,
    "학기": null,
    "필수선수": null,
    "권장선수": null,
    "실험실습": null,
    "세부전공": null,
    "학점": 1,
    "시간": 3,
    "전공역량": null,
    "대학": "이과대학",
    "학과": "수학과",
    "개설학과": "생명과학부",
    "내용": null,
    "메모": null,
    "개설횟수": 5
  },
  {
    "구분": "학문의기초",
    "학수번호": "MATH166",
    "교과목명": "수학을위한기초컴퓨팅",
    "학년": 2.0,
    "학기": 2.0,
    "필수선수": null,
    "권장선수": null,
    "실험실습": null,
    "세부전공": null,
    "학점": 3,
    "시간": 3,
    "전공역량": "미래 변화주도",
    "대학": "이과대학",
    "학과": "수학과",
    "개설학과": "수학과",
    "내용": null,
    "메모": null,
    "개설횟수": 3
  },
  {
    "구분": "전공필수",
    "학수번호": "MATH211",
    "교과목명": "해석학Ⅰ및연습",
    "학년": 2.0,
    "학기": 1.0,
    "필수선수": null,
    "권장선수": null,
    "실험실습": null,
    "세부전공": null,
    "학점": 3,
    "시간": 3,
    "전공역량": "수학적 지식과 사고",
    "대학": "이과대학",
    "학과": "수학과",
    "개설학과": "수학과",
    "내용": null,
    "메모": null,
    "개설횟수": 5
  },
  {
    "구분": "전공필수",
    "학수번호": "MATH212",
    "교과목명": "해석학Ⅱ및연습",
    "학년": 2.0,
    "학기": 2.0,
    "필수선수": null,
    "권장선수": null,
    "실험실습": null,
    "세부전공": null,
    "학점": 3,
    "시간": 3,
    "전공역량": "수학적 지식과 사고",
    "대학": "이과대학",
    "학과": "수학과",
    "개설학과": "수학과",
    "내용": null,
    "메모": null,
    "개설횟수": 5
  },
  {
    "구분": "전공필수",
    "학수번호": "MATH221",
    "교과목명": "선형대수Ⅰ및연습",
    "학년": 2.0,
    "학기": 1.0,
    "필수선수": null,
    "권장선수": null,
    "실험실습": null,
    "세부전공": null,
    "학점": 3,
    "시간": 3,
    "전공역량": "수학적 지식과 사고",
    "대학": "이과대학",
    "학과": "수학과",
    "개설학과": "수학과",
    "내용": null,
    "메모": null,
    "개설횟수": 5
  },
  {
    "구분": "전공필수",
    "학수번호": "MATH222",
    "교과목명": "선형대수Ⅱ및연습",
    "학년": 2.0,
    "학기": 2.0,
    "필수선수": null,
    "권장선수": null,
    "실험실습": null,
    "세부전공": null,
    "학점": 3,
    "시간": 3,
    "전공역량": "수학적 지식과 사고",
    "대학": "이과대학",
    "학과": "수학과",
    "개설학과": "수학과",
    "내용": null,
    "메모": null,
    "개설횟수": 5
  },
  {
    "구분": "전공필수",
    "학수번호": "MATH315",
    "교과목명": "복소해석학I",
    "학년": 3.0,
    "학기": 1.0,
    "필수선수": null,
    "권장선수": null,
    "실험실습": null,
    "세부전공": null,
    "학점": 3,
    "시간": 3,
    "전공역량": "수학적 지식과 사고",
    "대학": "이과대학",
    "학과": "수학과",
    "개설학과": "수학과",
    "내용": null,
    "메모": null,
    "개설횟수": 5
  },
  {
    "구분": "전공필수",
    "학수번호": "MATH321",
    "교과목명": "대수학Ⅰ",
    "학년": 3.0,
    "학기": 1.0,
    "필수선수": null,
    "권장선수": null,
    "실험실습": null,
    "세부전공": null,
    "학점": 3,
    "시간": 3,
    "전공역량": "수학적 지식과 사고",
    "대학": "이과대학",
    "학과": "수학과",
    "개설학과": "수학과",
    "내용": null,
    "메모": null,
    "개설횟수": 5
  },
  {
    "구분": "전공필수",
    "학수번호": "MATH331",
    "교과목명": "미분기하학Ⅰ",
    "학년": 3.0,
    "학기": 1.0,
    "필수선수": null,
    "권장선수": null,
    "실험실습": null,
    "세부전공": null,
    "학점": 3,
    "시간": 3,
    "전공역량": "수학적 지식과 사고",
    "대학": "이과대학",
    "학과": "수학과",
    "개설학과": "수학과",
    "내용": null,
    "메모": null,
    "개설횟수": 5
  },
  {
    "구분": "전공필수",
    "학수번호": "MATH333",
    "교과목명": "위상수학Ⅰ",
    "학년": 3.0,
    "학기": 1.0,
    "필수선수": null,
    "권장선수": null,
    "실험실습": null,
    "세부전공": null,
    "학점": 3,
    "시간": 3,
    "전공역량": "수학적 지식과 사고",
    "대학": "이과대학",
    "학과": "수학과",
    "개설학과": "수학과",
    "내용": null,
    "메모": null,
    "개설횟수": 5
  },
  {
    "구분": "전공선택",
    "학수번호": "MATH201",
    "교과목명": "집합론",
    "학년": 2.0,
    "학기": 1.0,
    "필수선수": null,
    "권장선수": null,
    "실험실습": null,
    "세부전공": null,
    "학점": 3,
    "시간": 3,
    "전공역량": "논리 및 추론",
    "대학": "이과대학",
    "학과": "수학과",
    "개설학과": "수학과",
    "내용": null,
    "메모": null,
    "개설횟수": 4
  },
  {
    "구분": "전공선택",
    "학수번호": "MATH203",
    "교과목명": "이산수학",
    "학년": 2.0,
    "학기": 1.0,
    "필수선수": null,
    "권장선수": null,
    "실험실습": null,
    "세부전공": null,
    "학점": 3,
    "시간": 3,
    "전공역량": "수학적 지식과 사고",
    "대학": "이과대학",
    "학과": "수학과",
    "개설학과": "수학과",
    "내용": null,
    "메모": null,
    "개설횟수": 5
  },
  {
    "구분": "전공선택",
    "학수번호": "MATH223",
    "교과목명": "정수론",
    "학년": 2.0,
    "학기": 1.0,
    "필수선수": null,
    "권장선수": null,
    "실험실습": null,
    "세부전공": null,
    "학점": 3,
    "시간": 3,
    "전공역량": "수학적 지식과 사고",
    "대학": "이과대학",
    "학과": "수학과",
    "개설학과": "수학과",
    "내용": null,
    "메모": null,
    "개설횟수": 4
  },
  {
    "구분": "전공선택",
    "학수번호": "MATH232",
    "교과목명": "기하학개론",
    "학년": 2.0,
    "학기": 2.0,
    "필수선수": null,
    "권장선수": null,
    "실험실습": null,
    "세부전공": null,
    "학점": 3,
    "시간": 3,
    "전공역량": "수학적 지식과 사고",
    "대학": "이과대학",
    "학과": "수학과",
    "개설학과": "수학과",
    "내용": null,
    "메모": null,
    "개설횟수": 5
  },
  {
    "구분": "전공선택",
    "학수번호": "MATH240",
    "교과목명": "미분방정식및연습",
    "학년": 2.0,
    "학기": 2.0,
    "필수선수": null,
    "권장선수": null,
    "실험실습": null,
    "세부전공": null,
    "학점": 3,
    "시간": 3,
    "전공역량": "창의적 문제해결",
    "대학": "이과대학",
    "학과": "수학과",
    "개설학과": "수학과",
    "내용": null,
    "메모": null,
    "개설횟수": 5
  },
  {
    "구분": "전공선택",
    "학수번호": "MATH282",
    "교과목명": "미분방정식론",
    "학년": 2.0,
    "학기": 2.0,
    "필수선수": null,
    "권장선수": null,
    "실험실습": null,
    "세부전공": null,
    "학점": 3,
    "시간": 3,
    "전공역량": "수학적 지식과 사고",
    "대학": "이과대학",
    "학과": "수학과",
    "개설학과": "수학과",
    "내용": null,
    "메모": null,
    "개설횟수": 2
  },
  {
    "구분": "전공선택",
    "학수번호": "MATH292",
    "교과목명": "인공지능의수학적기초",
    "학년": 2.0,
    "학기": 2.0,
    "필수선수": null,
    "권장선수": null,
    "실험실습": null,
    "세부전공": null,
    "학점": 3,
    "시간": 3,
    "전공역량": "미래 변화주도",
    "대학": "이과대학",
    "학과": "수학과",
    "개설학과": "수학과",
    "내용": null,
    "메모": null,
    "개설횟수": 4
  },
  {
    "구분": "전공선택",
    "학수번호": "MATH342",
    "교과목명": "수치해석및연습",
    "학년": 3.0,
    "학기": 2.0,
    "필수선수": null,
    "권장선수": null,
    "실험실습": null,
    "세부전공": null,
    "학점": 3,
    "시간": 3,
    "전공역량": "논리 및 추론",
    "대학": "이과대학",
    "학과": "수학과",
    "개설학과": "수학과",
    "내용": null,
    "메모": null,
    "개설횟수": 3
  },
  {
    "구분": "전공선택",
    "학수번호": "MATH343",
    "교과목명": "확률과통계및연습",
    "학년": 3.0,
    "학기": 1.0,
    "필수선수": null,
    "권장선수": null,
    "실험실습": null,
    "세부전공": null,
    "학점": 3,
    "시간": 3,
    "전공역량": "수학적 지식과 사고",
    "대학": "이과대학",
    "학과": "수학과",
    "개설학과": "수학과",
    "내용": null,
    "메모": null,
    "개설횟수": 5
  },
  {
    "구분": "전공선택",
    "학수번호": "MATH344",
    "교과목명": "확률과정개론",
    "학년": 3.0,
    "학기": 2.0,
    "필수선수": null,
    "권장선수": null,
    "실험실습": null,
    "세부전공": null,
    "학점": 3,
    "시간": 3,
    "전공역량": "수학적 지식과 사고",
    "대학": "이과대학",
    "학과": "수학과",
    "개설학과": "수학과",
    "내용": null,
    "메모": null,
    "개설횟수": 4
  },
  {
    "구분": "전공선택",
    "학수번호": "MATH358",
    "교과목명": "복소해석학II",
    "학년": 3.0,
    "학기": 2.0,
    "필수선수": null,
    "권장선수": null,
    "실험실습": null,
    "세부전공": null,
    "학점": 3,
    "시간": 3,
    "전공역량": "수학적 지식과 사고",
    "대학": "이과대학",
    "학과": "수학과",
    "개설학과": "수학과",
    "내용": null,
    "메모": null,
    "개설횟수": 5
  },
  {
    "구분": "전공선택",
    "학수번호": "MATH362",
    "교과목명": "대수학Ⅱ",
    "학년": 3.0,
    "학기": 2.0,
    "필수선수": null,
    "권장선수": null,
    "실험실습": null,
    "세부전공": null,
    "학점": 3,
    "시간": 3,
    "전공역량": "수학적 지식과 사고",
    "대학": "이과대학",
    "학과": "수학과",
    "개설학과": "수학과",
    "내용": null,
    "메모": null,
    "개설횟수": 5
  },
  {
    "구분": "전공선택",
    "학수번호": "MATH372",
    "교과목명": "미분기하학Ⅱ",
    "학년": 3.0,
    "학기": 2.0,
    "필수선수": null,
    "권장선수": null,
    "실험실습": null,
    "세부전공": null,
    "학점": 3,
    "시간": 3,
    "전공역량": "수학적 지식과 사고",
    "대학": "이과대학",
    "학과": "수학과",
    "개설학과": "수학과",
    "내용": null,
    "메모": null,
    "개설횟수": 2
  },
  {
    "구분": "전공선택",
    "학수번호": "MATH374",
    "교과목명": "위상수학II",
    "학년": 3.0,
    "학기": 2.0,
    "필수선수": null,
    "권장선수": null,
    "실험실습": null,
    "세부전공": null,
    "학점": 3,
    "시간": 3,
    "전공역량": "수학적 지식과 사고",
    "대학": "이과대학",
    "학과": "수학과",
    "개설학과": "수학과",
    "내용": null,
    "메모": null,
    "개설횟수": 4
  },
  {
    "구분": "전공선택",
    "학수번호": "MATH391",
    "교과목명": "딥러닝의수학",
    "학년": 3.0,
    "학기": 1.0,
    "필수선수": null,
    "권장선수": null,
    "실험실습": null,
    "세부전공": null,
    "학점": 3,
    "시간": 3,
    "전공역량": "미래 변화주도",
    "대학": "이과대학",
    "학과": "수학과",
    "개설학과": "수학과",
    "내용": null,
    "메모": null,
    "개설횟수": 3
  },
  {
    "구분": "전공선택",
    "학수번호": "MATH392",
    "교과목명": "강화학습의수학",
    "학년": 3.0,
    "학기": 2.0,
    "필수선수": null,
    "권장선수": null,
    "실험실습": null,
    "세부전공": null,
    "학점": 3,
    "시간": 3,
    "전공역량": "미래 변화주도",
    "대학": "이과대학",
    "학과": "수학과",
    "개설학과": "수학과",
    "내용": null,
    "메모": null,
    "개설횟수": 2
  },
  {
    "구분": "전공선택",
    "학수번호": "MATH453",
    "교과목명": "실해석학",
    "학년": 4.0,
    "학기": 1.0,
    "필수선수": null,
    "권장선수": null,
    "실험실습": null,
    "세부전공": null,
    "학점": 3,
    "시간": 3,
    "전공역량": "수학적 지식과 사고",
    "대학": "이과대학",
    "학과": "수학과",
    "개설학과": "수학과",
    "내용": null,
    "메모": null,
    "개설횟수": 5
  },
  {
    "구분": "전공선택",
    "학수번호": "MATH458",
    "교과목명": "해석학특강",
    "학년": 4.0,
    "학기": 2.0,
    "필수선수": null,
    "권장선수": null,
    "실험실습": null,
    "세부전공": null,
    "학점": 3,
    "시간": 3,
    "전공역량": "수학적 지식과 사고",
    "대학": "이과대학",
    "학과": "수학과",
    "개설학과": "수학과",
    "내용": null,
    "메모": null,
    "개설횟수": 1
  },
  {
    "구분": "전공선택",
    "학수번호": "MATH462",
    "교과목명": "응용정수론",
    "학년": 4.0,
    "학기": 2.0,
    "필수선수": null,
    "권장선수": null,
    "실험실습": null,
    "세부전공": null,
    "학점": 3,
    "시간": 3,
    "전공역량": "수학적 지식과 사고",
    "대학": "이과대학",
    "학과": "수학과",
    "개설학과": "수학과",
    "내용": null,
    "메모": null,
    "개설횟수": 3
  },
  {
    "구분": "전공선택",
    "학수번호": "MATH464",
    "교과목명": "조합론",
    "학년": 4.0,
    "학기": 2.0,
    "필수선수": null,
    "권장선수": null,
    "실험실습": null,
    "세부전공": null,
    "학점": 3,
    "시간": 3,
    "전공역량": "수학적 지식과 사고",
    "대학": "이과대학",
    "학과": "수학과",
    "개설학과": "수학과",
    "내용": null,
    "메모": null,
    "개설횟수": 3
  },
  {
    "구분": "전공선택",
    "학수번호": "MATH469",
    "교과목명": "대수학특강",
    "학년": 4.0,
    "학기": 1.0,
    "필수선수": null,
    "권장선수": null,
    "실험실습": null,
    "세부전공": null,
    "학점": 3,
    "시간": 3,
    "전공역량": "수학적 지식과 사고",
    "대학": "이과대학",
    "학과": "수학과",
    "개설학과": "수학과",
    "내용": null,
    "메모": null,
    "개설횟수": 3
  },
  {
    "구분": "전공선택",
    "학수번호": "MATH481",
    "교과목명": "편미분방정식및연습",
    "학년": 4.0,
    "학기": 1.0,
    "필수선수": null,
    "권장선수": null,
    "실험실습": null,
    "세부전공": null,
    "학점": 3,
    "시간": 3,
    "전공역량": "수학적 지식과 사고",
    "대학": "이과대학",
    "학과": "수학과",
    "개설학과": "수학과",
    "내용": null,
    "메모": null,
    "개설횟수": 4
  },
  {
    "구분": "전공선택",
    "학수번호": "MATH483",
    "교과목명": "금융수학",
    "학년": 4.0,
    "학기": 1.0,
    "필수선수": null,
    "권장선수": null,
    "실험실습": null,
    "세부전공": null,
    "학점": 3,
    "시간": 3,
    "전공역량": "미래 변화주도",
    "대학": "이과대학",
    "학과": "수학과",
    "개설학과": "수학과",
    "내용": null,
    "메모": null,
    "개설횟수": 1
  },
  {
    "구분": "전공선택",
    "학수번호": "MATH484",
    "교과목명": "보험수학",
    "학년": 4.0,
    "학기": 2.0,
    "필수선수": null,
    "권장선수": null,
    "실험실습": null,
    "세부전공": null,
    "학점": 3,
    "시간": 3,
    "전공역량": "미래 변화주도",
    "대학": "이과대학",
    "학과": "수학과",
    "개설학과": "수학과",
    "내용": null,
    "메모": null,
    "개설횟수": 2
  },
  {
    "구분": "전공선택",
    "학수번호": "MATH487",
    "교과목명": "응용수학특강",
    "학년": 4.0,
    "학기": 2.0,
    "필수선수": null,
    "권장선수": null,
    "실험실습": null,
    "세부전공": null,
    "학점": 3,
    "시간": 3,
    "전공역량": "미래 변화주도",
    "대학": "이과대학",
    "학과": "수학과",
    "개설학과": "수학과",
    "내용": null,
    "메모": null,
    "개설횟수": 5
  },
  {
    "구분": "전공선택",
    "학수번호": "MATH488",
    "교과목명": "확률론특강",
    "학년": 4.0,
    "학기": 2.0,
    "필수선수": null,
    "권장선수": null,
    "실험실습": null,
    "세부전공": null,
    "학점": 3,
    "시간": 3,
    "전공역량": "수학적 지식과 사고",
    "대학": "이과대학",
    "학과": "수학과",
    "개설학과": "수학과",
    "내용": null,
    "메모": null,
    "개설횟수": 2
  },
  {
    "구분": "전공선택",
    "학수번호": "MATH491",
    "교과목명": "인공지능의수학적기법",
    "학년": 4.0,
    "학기": 1.0,
    "필수선수": null,
    "권장선수": null,
    "실험실습": null,
    "세부전공": null,
    "학점": 3,
    "시간": 3,
    "전공역량": "미래 변화주도",
    "대학": "이과대학",
    "학과": "수학과",
    "개설학과": "수학과",
    "내용": null,
    "메모": null,
    "개설횟수": 1
  }
]
